{
  "letters": [
    {
      "createdAt": "2023-12-01T15:16:12.182Z",
      "nickname": "멋진르탄",
      "avatar": "https://react-jwt-avatar.s3.ap-northeast-2.amazonaws.com/23-12-01/62d91b9d-694c-4ec1-b996-e0cd5233d66f.jpg",
      "content": "aaa",
      "writedTo": "효정",
      "id": "fb3551e1-7689-4cab-a639-17efddde6519",
      "userId": "dkshk"
    },
    {
      "createdAt": "2023-12-01T15:17:12.183Z",
      "nickname": "안녕하세요?",
      "avatar": "https://react-jwt-avatar.s3.ap-northeast-2.amazonaws.com/23-12-01/483457a1-e8cc-4560-aec6-a40e76a02ff8.jpg",
      "content": "안녕하세요",
      "writedTo": "미미",
      "id": "16a8b4f9-4754-420d-8a21-e6386140f5f2",
      "userId": "dkssudgksr"
    },
    {
      "createdAt": "2023-12-01T15:18:41.444Z",
      "nickname": "12345",
      "avatar": "https://react-jwt-avatar.s3.ap-northeast-2.amazonaws.com/23-12-01/92fc9bdc-0237-4843-b5e0-6099481c10f3.jpg",
      "content": "되는건가 수정까지ㅁ",
      "writedTo": "유아",
      "id": "dc00e86e-f010-4313-9652-608371e40d1c",
      "userId": "12345"
    },
    {
      "createdAt": "2023-12-01T15:20:32.401Z",
      "nickname": "12345",
      "avatar": "https://react-jwt-avatar.s3.ap-northeast-2.amazonaws.com/23-12-01/92fc9bdc-0237-4843-b5e0-6099481c10f3.jpg",
      "content": "만들어왑",
      "writedTo": "유빈",
      "id": "54f4f13c-c282-41fb-b96b-ccb2e1965c25",
      "userId": "12345"
    },
    {
      "createdAt": "2023-12-01T15:29:13.640Z",
      "nickname": "이름을 바꾸면?",
      "avatar": "https://react-jwt-avatar.s3.ap-northeast-2.amazonaws.com/23-12-01/0e341d14-c12a-4fac-ae1e-78992faff50a.jpg",
      "content": "뭐야",
      "writedTo": "효정",
      "id": "de6b4cd7-fa1c-42ee-a3a2-9bb212ca07e2",
      "userId": "12345"
    },
    {
      "createdAt": "2023-12-01T15:31:56.801Z",
      "nickname": "멋진르탄",
      "avatar": "https://react-jwt-avatar.s3.ap-northeast-2.amazonaws.com/23-12-01/62d91b9d-694c-4ec1-b996-e0cd5233d66f.jpg",
      "content": "aa",
      "writedTo": "효정",
      "id": "6e833be0-e4ca-4920-97eb-4e987651acc2",
      "userId": "dkshk"
    },
    {
      "createdAt": "2023-12-01T15:34:01.747Z",
      "nickname": "멋진르탄",
      "avatar": "https://react-jwt-avatar.s3.ap-northeast-2.amazonaws.com/23-12-01/62d91b9d-694c-4ec1-b996-e0cd5233d66f.jpg",
      "content": "aaaaaaaaaaaa",
      "writedTo": "효정",
      "id": "9e8425f9-244d-41d9-b289-2011cfb29b3c",
      "userId": "dkshk"
    }
  ]
}